analysishelper/__init__.py
analysishelper/map/__init__.py
analysishelper/map/categorymap.py
analysishelper/map/periodmap.py
analysishelper/map/metadata/config.ini
analysishelper/map/metadata/period_dict.xlsx
analysishelper/utils/__init__.py
analysishelper/utils/customdatetime.py
analysishelper/utils/customfilesys.py
analysishelper/utils/customlog.py
analysishelper/utils/outputgen.py
analysishelper-0.0.5.dist-info/LICENSE
analysishelper-0.0.5.dist-info/METADATA
analysishelper-0.0.5.dist-info/WHEEL
analysishelper-0.0.5.dist-info/top_level.txt
analysishelper-0.0.5.dist-info/RECORD
