Metadata-Version: 2.1
Name: analysishelper
Version: 0.0.5
Summary: The help you need in data analysis
Author: codenamewei
Author-email: <codenamewei@gmail.com>
License: UNKNOWN
Platform: UNKNOWN
Classifier: Programming Language :: Python :: 3
Classifier: License :: OSI Approved :: MIT License
Classifier: Operating System :: OS Independent
Requires-Python: >=3.6
License-File: LICENSE
Requires-Dist: pandas (>=1.1.5)
Requires-Dist: numpy (>1.21)
